hxeva/__init__.py
hxeva/_version.py
hxeva/evaluate/__init__.py
hxeva/evaluate/base.py
hxeva/evaluate/score.py
hxeva/evaluate/space.py
hxeva/evaluate/stats.py
hxeva/log/__init__.py
hxeva/log/logger.py
hxeva/meteorology/__init__.py
hxeva/meteorology/constant.py
hxeva/meteorology/utils/__init__.py
hxeva/meteorology/utils/calc.py
hxeva/meteorology/utils/data.py
hxeva/product/__init__.py
hxeva/product/art1km.py
hxeva/product/base.py
hxeva/product/config.py
hxeva/product/convection.py
hxeva/product/grid.py
hxeva/product/station.py
hxeva/product/swan.py
hxeva/product/yunnan_er.py
hxeva/utils/__init__.py
hxeva/utils/administration.py
hxeva/utils/interpolate.py
hxeva/utils/path.py
hxeva/utils/pool.py
hxeva/utils/upsample.py
hxeva/utils/visualization.py
hxeva-2.0.1b0.dist-info/LICENSE
hxeva-2.0.1b0.dist-info/METADATA
hxeva-2.0.1b0.dist-info/WHEEL
hxeva-2.0.1b0.dist-info/top_level.txt
hxeva-2.0.1b0.dist-info/RECORD
