Metadata-Version: 2.1
Name: hxeva
Version: 2.0.1b0
Author: Fang Linwanghao
Author-email: fanglinwanghao@cnpresky.com
License: BSD-3-Clause
License-File: LICENSE
Requires-Dist: opencv (~=4.5.5)
Requires-Dist: netCDF4 (~=1.6.0)
Requires-Dist: numpy (~=1.19.5)
Requires-Dist: pandas (~=1.3.5)
Requires-Dist: pygrib (~=2.1.4)
Requires-Dist: scikit-image (~=0.18.1)
Requires-Dist: scipy (~=1.5.3)
